LICENSE.txt
MANIFEST.in
README.md
setup.cfg
setup.py
topsis/102003243.py
topsis/__init__.py
topsis_bishanpreet_102003243.egg-info/PKG-INFO
topsis_bishanpreet_102003243.egg-info/SOURCES.txt
topsis_bishanpreet_102003243.egg-info/dependency_links.txt
topsis_bishanpreet_102003243.egg-info/top_level.txt