Metadata-Version: 2.1
Name: topsis-bishanpreet-102003243
Version: 1.0.1
Summary: topsis implementation
Author: Bishanpreet Kaur
Author-email: bgill_be20@thapar.edu
Classifier: Programming Language :: Python :: 3
Classifier: License :: OSI Approved :: MIT License
Classifier: Operating System :: OS Independent
Requires-Python: >=3.6
License-File: LICENSE.txt
